{"237650883798@s.whatsapp.net":true,"237696602774@s.whatsapp.net":true,"237696602774:17@s.whatsapp.net":true,"237696602774:18@s.whatsapp.net":true,"237696602774:19@s.whatsapp.net":true,"237696602774:20@s.whatsapp.net":true,"237656871002@s.whatsapp.net":true,"23756784784@s.whatsapp.net":true,"233271518001@s.whatsapp.net":true,"237655875121@s.whatsapp.net":true,"23791633571@s.whatsapp.net":true,"23756064266@s.whatsapp.net":true,"23797634747@s.whatsapp.net":true,"23756524859@s.whatsapp.net":true,"23672135783@s.whatsapp.net":true,"237657234606@s.whatsapp.net":true,"23778111310@s.whatsapp.net":true,"14167227124@s.whatsapp.net":true,"237693936731@s.whatsapp.net":true,"23675317969@s.whatsapp.net":true,"237680301678@s.whatsapp.net":true,"237698368231@s.whatsapp.net":true,"237670906406@s.whatsapp.net":true,"23565909343@s.whatsapp.net":true,"237699635714@s.whatsapp.net":true,"237674243452@s.whatsapp.net":true,"237657688993@s.whatsapp.net":true,"237673445573@s.whatsapp.net":true,"237655050024@s.whatsapp.net":true,"237694855561@s.whatsapp.net":true,"237691676179@s.whatsapp.net":true,"237656723172@s.whatsapp.net":true,"237697507909@s.whatsapp.net":true,"23798421790@s.whatsapp.net":true,"23774679926@s.whatsapp.net":true,"237656706490@s.whatsapp.net":true,"237693030641@s.whatsapp.net":true,"237652647859@s.whatsapp.net":true,"23675508260@s.whatsapp.net":true,"237690172375@s.whatsapp.net":true,"237690172375:1@s.whatsapp.net":true,"237690175219@s.whatsapp.net":true,"237695484814@s.whatsapp.net":true,"237695484814:22@s.whatsapp.net":true,"237690956472@s.whatsapp.net":true,"237696684490@s.whatsapp.net":true,"23674126261@s.whatsapp.net":true,"237691467446@s.whatsapp.net":true,"237658263231@s.whatsapp.net":true,"23756889293@s.whatsapp.net":true,"237659440981@s.whatsapp.net":true,"23755781719@s.whatsapp.net":true,"237691553596@s.whatsapp.net":true,"237698231442@s.whatsapp.net":true,"237678943190@s.whatsapp.net":true,"237699789098@s.whatsapp.net":true,"237698369326@s.whatsapp.net":true,"237693209998@s.whatsapp.net":true,"237694712817@s.whatsapp.net":true,"237672531694@s.whatsapp.net":true,"237699227980@s.whatsapp.net":true,"23670010774@s.whatsapp.net":true,"237695080944@s.whatsapp.net":true,"237699509005@s.whatsapp.net":true,"237697991525@s.whatsapp.net":true,"237655112034@s.whatsapp.net":true,"237691593227@s.whatsapp.net":true,"237698447348@s.whatsapp.net":true,"23672532888@s.whatsapp.net":true,"237694838818@s.whatsapp.net":true,"237656647095@s.whatsapp.net":true,"237656647095:38@s.whatsapp.net":true,"23793314914@s.whatsapp.net":true,"237674571291@s.whatsapp.net":true,"237674571291:8@s.whatsapp.net":true,"237699398776@s.whatsapp.net":true,"237699398776:15@s.whatsapp.net":true,"23798657542@s.whatsapp.net":true,"237656739129@s.whatsapp.net":true,"237691679255@s.whatsapp.net":true,"237658662621@s.whatsapp.net":true,"237654139231@s.whatsapp.net":true,"237690653508@s.whatsapp.net":true,"221771697363@s.whatsapp.net":true,"221771697363:4@s.whatsapp.net":true,"237696176335@s.whatsapp.net":true,"237690938640@s.whatsapp.net":true,"23778883376@s.whatsapp.net":true,"237691372695@s.whatsapp.net":true,"23790255517@s.whatsapp.net":true,"242067145785@s.whatsapp.net":true,"237696821765@s.whatsapp.net":true,"237655887274@s.whatsapp.net":true,"23755401170@s.whatsapp.net":true,"237659254293@s.whatsapp.net":true,"237656621151@s.whatsapp.net":true,"237690273910@s.whatsapp.net":true,"23791670626@s.whatsapp.net":true,"237692237783@s.whatsapp.net":true,"23797127211@s.whatsapp.net":true,"23794030722@s.whatsapp.net":true,"237654518107@s.whatsapp.net":true,"23755110551@s.whatsapp.net":true,"237656523580@s.whatsapp.net":true,"23791106958@s.whatsapp.net":true,"237696938053@s.whatsapp.net":true,"237696938053:4@s.whatsapp.net":true,"237696938053:5@s.whatsapp.net":true,"237696938053:6@s.whatsapp.net":true,"237675624990@s.whatsapp.net":true,"237693796350@s.whatsapp.net":true,"237690388929@s.whatsapp.net":true,"237657531680@s.whatsapp.net":true,"23755757463@s.whatsapp.net":true,"237676881373@s.whatsapp.net":true,"237676881373:4@s.whatsapp.net":true,"237694338308@s.whatsapp.net":true,"237690335213@s.whatsapp.net":true,"237697527241@s.whatsapp.net":true,"237699259563@s.whatsapp.net":true,"237691923838@s.whatsapp.net":true,"237699802729@s.whatsapp.net":true,"237655634306@s.whatsapp.net":true,"237657961823@s.whatsapp.net":true,"237659248502@s.whatsapp.net":true,"237697086965@s.whatsapp.net":true,"237699818984@s.whatsapp.net":true,"23793558797@s.whatsapp.net":true,"237696388443@s.whatsapp.net":true,"23563187589@s.whatsapp.net":true,"23566985019@s.whatsapp.net":true}