{"237650883798@s.whatsapp.net":true,"237695043995@s.whatsapp.net":true,"237694963374@s.whatsapp.net":true,"237693294442@s.whatsapp.net":true,"237691633727@s.whatsapp.net":true,"237681812681@s.whatsapp.net":true,"237676609873@s.whatsapp.net":true,"237676470297@s.whatsapp.net":true,"237672667239@s.whatsapp.net":true,"237659578909@s.whatsapp.net":true,"237653747820@s.whatsapp.net":true,"237652141255@s.whatsapp.net":true,"237651721759@s.whatsapp.net":true,"22892482063@s.whatsapp.net":true,"22509977980@s.whatsapp.net":true,"221781895023@s.whatsapp.net":true}