{"237695308589@s.whatsapp.net":true,"237650883798@s.whatsapp.net":true,"33615641467:88@s.whatsapp.net":true,"22578572689@s.whatsapp.net":true,"22967879902@s.whatsapp.net":true,"22954232728@s.whatsapp.net":true,"237656977508@s.whatsapp.net":true,"237653003113@s.whatsapp.net":true,"22576051777@s.whatsapp.net":true,"22576051777:51@s.whatsapp.net":true,"22870543883@s.whatsapp.net":true,"22559749470@s.whatsapp.net":true,"22559749470:3@s.whatsapp.net":true,"22559749470:4@s.whatsapp.net":true,"22370925462@s.whatsapp.net":true,"243844347013@s.whatsapp.net":true,"22963434150@s.whatsapp.net":true,"22963434150:5@s.whatsapp.net":true,"2349013995724@s.whatsapp.net":true,"22594562893@s.whatsapp.net":true,"21656815240@s.whatsapp.net":true,"242064940780@s.whatsapp.net":true,"2250705480294@s.whatsapp.net":true,"22962777578@s.whatsapp.net":true,"22548210666@s.whatsapp.net":true,"237691155527@s.whatsapp.net":true,"22896306072@s.whatsapp.net":true,"22990574449@s.whatsapp.net":true,"22557238569@s.whatsapp.net":true,"22589709869@s.whatsapp.net":true,"22589709869:17@s.whatsapp.net":true,"13257355054@s.whatsapp.net":true,"22377288763@s.whatsapp.net":true,"22377288763:45@s.whatsapp.net":true,"22893276393@s.whatsapp.net":true,"237676164015@s.whatsapp.net":true,"22391857475@s.whatsapp.net":true,"24102000480@s.whatsapp.net":true,"22550164859@s.whatsapp.net":true,"22574444701@s.whatsapp.net":true,"22891442720@s.whatsapp.net":true,"22891442720:94@s.whatsapp.net":true,"33623302799@s.whatsapp.net":true,"22504416190@s.whatsapp.net":true,"22504416190:1@s.whatsapp.net":true,"22577766701@s.whatsapp.net":true,"243813030152@s.whatsapp.net":true,"237697338947@s.whatsapp.net":true,"221706473430@s.whatsapp.net":true,"23569746496@s.whatsapp.net":true,"22654540141@s.whatsapp.net":true,"22870392473@s.whatsapp.net":true,"22595147835@s.whatsapp.net":true,"243999228903@s.whatsapp.net":true,"2349019620777@s.whatsapp.net":true,"237679170836@s.whatsapp.net":true,"22588992438@s.whatsapp.net":true,"237696813190@s.whatsapp.net":true,"22879434025@s.whatsapp.net":true,"22961809807@s.whatsapp.net":true,"22596212622@s.whatsapp.net":true,"2250500866308@s.whatsapp.net":true,"2349157065295@s.whatsapp.net":true,"22670950357@s.whatsapp.net":true,"22382951694@s.whatsapp.net":true,"22553860996@s.whatsapp.net":true,"243970267153@s.whatsapp.net":true,"22383217280@s.whatsapp.net":true,"237657072340@s.whatsapp.net":true,"237658500829@s.whatsapp.net":true,"22879787668@s.whatsapp.net":true,"22962629409@s.whatsapp.net":true,"22997609224@s.whatsapp.net":true,"22896083923@s.whatsapp.net":true,"237656293602@s.whatsapp.net":true,"237693034216@s.whatsapp.net":true,"24102551295@s.whatsapp.net":true,"243851553048@s.whatsapp.net":true}